boilercine/__init__.py
boilercine/models.py
boilercine/types.py
boilercine-2024.1.2.dist-info/LICENSE
boilercine-2024.1.2.dist-info/WHEEL
boilercine-2024.1.2.dist-info/METADATA
boilercine-2024.1.2.dist-info/RECORD
