Metadata-Version: 2.1
Name: boilercine
Version: 2024.1.2
Summary: Convert CINEs for a boiling study
Author-email: Blake Naccarato <blake.naccarato@gmail.com>
Requires-Python: >=3.11
Classifier: License :: OSI Approved :: MIT License
Classifier: Programming Language :: Python :: 3.11
Classifier: Programming Language :: Python :: 3.12
Requires-Dist: click>=8.1.7
Requires-Dist: colorama>=0.4.6
Requires-Dist: docopt>=0.6.2
Requires-Dist: numpy>=1.26.0
Requires-Dist: timecode>=1.4.0
Requires-Dist: opencv-python-headless>=4.9.0.80 ; extra == "cv"
Project-URL: Changes, https://softboiler.github.io/boilercine/changelog.html
Project-URL: Docs, https://softboiler.github.io/boilercine
Project-URL: Home, https://github.com/softboiler/boilercine
Project-URL: Tracker, https://github.com/softboiler/boilercine/issues
Provides-Extra: cv
